plaintext_password/__init__.py
plaintext_password/checks.py
plaintext_password/py.typed
django_plaintext_password-0.3.0.dist-info/LICENSE
django_plaintext_password-0.3.0.dist-info/METADATA
django_plaintext_password-0.3.0.dist-info/WHEEL
django_plaintext_password-0.3.0.dist-info/top_level.txt
django_plaintext_password-0.3.0.dist-info/RECORD
