Metadata-Version: 2.1
Name: django-plaintext-password
Version: 0.3.0
Summary: A Django password hasher to store passwords in plaintext.
Author: Jake Howard
License: MIT License
Project-URL: Source, https://github.com/RealOrangeOne/django-plaintext-password
Project-URL: Issues, https://github.com/RealOrangeOne/django-plaintext-password/issues
Project-URL: Changelog, https://github.com/RealOrangeOne/django-plaintext-password/releases
Classifier: Development Status :: 5 - Production/Stable
Classifier: Environment :: Web Environment
Classifier: Framework :: Django
Classifier: Framework :: Django :: 4.2
Classifier: Framework :: Django :: 5.0
Classifier: Framework :: Django :: 5.1
Classifier: Intended Audience :: Developers
Classifier: License :: OSI Approved :: BSD License
Classifier: Operating System :: OS Independent
Classifier: Programming Language :: Python :: 3.9
Classifier: Programming Language :: Python :: 3.10
Classifier: Programming Language :: Python :: 3.11
Classifier: Programming Language :: Python :: 3.12
Classifier: Programming Language :: Python :: 3.13
Classifier: Programming Language :: Python :: 3
Classifier: Programming Language :: Python
Classifier: Topic :: Internet :: WWW/HTTP
Classifier: Topic :: Software Development
Classifier: Typing :: Typed
Requires-Python: >=3.9
License-File: LICENSE
Requires-Dist: Django >=4.2
